Random_Data_Generator/EvidenceTheory.py
Random_Data_Generator/FuzzyTheory.py
Random_Data_Generator/ProbabilityTheory.py
Random_Data_Generator/__init__.py
RndGenerator/EvidenceTheory.py
RndGenerator/FuzzyTheory.py
RndGenerator/ProbabilityTheory.py
RndGenerator/__init__.py
RndGenerator-1.0.4.2.dist-info/LICENSE.txt
RndGenerator-1.0.4.2.dist-info/METADATA
RndGenerator-1.0.4.2.dist-info/WHEEL
RndGenerator-1.0.4.2.dist-info/top_level.txt
RndGenerator-1.0.4.2.dist-info/RECORD
