Metadata-Version: 2.1
Name: RndGenerator
Version: 1.0.4.2
Summary: Random data generator under small sample size
Author: BUAA
License: UNKNOWN
Platform: UNKNOWN
Classifier: Development Status :: 3 - Alpha
Classifier: Intended Audience :: Developers
Classifier: Topic :: Software Development :: Build Tools
Classifier: License :: OSI Approved :: MIT License
Classifier: Programming Language :: Python :: 3
Classifier: Programming Language :: Python :: 3.6
Classifier: Programming Language :: Python :: 3.7
Classifier: Programming Language :: Python :: 3.8
Classifier: Programming Language :: Python :: 3.9
Classifier: Programming Language :: Python :: 3.10
Classifier: Programming Language :: Python :: 3 :: Only
Requires-Python: >=3.6, <4
License-File: LICENSE.txt
Requires-Dist: setuptools (>=58.2.0)
Requires-Dist: numpy (>=1.19.5)
Requires-Dist: scipy (>=1.7.1)
Requires-Dist: matplotlib (>=3.4.3)
Requires-Dist: seaborn (>=0.11.2)
